tsetmcpy/__init__.py
tsetmcpy-0.0.4.dist-info/LICENSE
tsetmcpy-0.0.4.dist-info/METADATA
tsetmcpy-0.0.4.dist-info/WHEEL
tsetmcpy-0.0.4.dist-info/top_level.txt
tsetmcpy-0.0.4.dist-info/RECORD
