Metadata-Version: 2.1
Name: tsetmcpy
Version: 0.0.4
Summary: extract data from tsetmc
Home-page: https://github.com/PicInfiniti/tsetmc
Author: picinfiniti
Author-email: picinfiniti@gmail.com
Project-URL: Bug Tracker, https://github.com/PicInfiniti/tsetmc/issues
Classifier: Programming Language :: Python :: 3
Classifier: License :: OSI Approved :: MIT License
Classifier: Operating System :: OS Independent
Requires-Python: >=3.
License-File: LICENSE
